boa_test_constructor-0.7.0.dist-info/licenses/LICENSE.rst
boaconstructor/__init__.py
boaconstructor/node.py
boaconstructor/storage.py
boaconstructor/data/neogo
boaconstructor/data/protocol.unittest.yml
boaconstructor/data/wallet1_solo.json
boa_test_constructor-0.7.0.dist-info/METADATA
boa_test_constructor-0.7.0.dist-info/WHEEL
boa_test_constructor-0.7.0.dist-info/top_level.txt
boa_test_constructor-0.7.0.dist-info/RECORD
