Metadata-Version: 2.4
Name: boa_test_constructor
Version: 0.7.0
Summary: This project provides a unittest class for testing NEO3 Blockchain smart contracts
Author: Lucas Kenji Uezo, meevee98
Author-email: Erik van den Brink <erik@coz.io>
License: Copyright (c) 2023-present COZ
Project-URL: Repository, https://github.com/CityOfZion/boa-test-constructor
Keywords: NEO3,Blockchain,unit test
Requires-Python: <3.15,>=3.13
License-File: LICENSE.rst
Requires-Dist: neo-mamba==3.3.0
Requires-Dist: PyYAML
Requires-Dist: typing-extensions
Provides-Extra: dev
Requires-Dist: black==25.12.0; extra == "dev"
Requires-Dist: build==0.10.0; extra == "dev"
Requires-Dist: bump-my-version==0.10.0; extra == "dev"
Requires-Dist: mypy==1.16.0; extra == "dev"
Requires-Dist: requests; extra == "dev"
Requires-Dist: tomlkit==0.12.1; extra == "dev"
Requires-Dist: types-PyYAML; extra == "dev"
Dynamic: license-file
